[
    {
        "firstName": "GURUPRAKASH",
        "lastName": "V K ",
        "email": "developerguru03@gmail.com",
        "phone": "9095064152",
        "streetAddress": "xyz ,perundurai",
        "city": "erode ",
        "state": "Tamilnadu",
        "postalCode": "638057",
        "country": "Hong Kong",
        "product": "Business Internet 500 Mbps",
        "quantity": 4,
        "unitPrice": 200,
        "totalAmount": 800,
        "status": "Pending",
        "createdBy": "Mr. Ryan Cooper",
        "orderDate": "2026-03-16",
        "id": "94c09215-eded-465f-9ff9-f8bedfaa9b34"
    },
    {
        "firstName": "SUMANBABU",
        "lastName": "S",
        "email": "sumanbabu368@gmail.com",
        "phone": "08925708902",
        "streetAddress": "625513",
        "city": "Theni",
        "state": "Tamil Nadu",
        "postalCode": "625513",
        "country": "Canada",
        "product": "5G Unlimited Mobile Plan",
        "quantity": 3,
        "unitPrice": 549,
        "totalAmount": 1647,
        "status": "In progress",
        "createdBy": "Ms. Olivia Carter",
        "orderDate": "2026-03-17",
        "id": "cbe8df5c-4ef2-4f36-9b39-ad2ccbbcdee2"
    },
    {
        "firstName": "GURUPRAKASH",
        "lastName": "K",
        "email": "guruprakashvk39@gmail.com",
        "phone": "9095064152",
        "streetAddress": "xxxxxx",
        "city": "xxxxx",
        "state": "xxxxxx",
        "postalCode": "76767",
        "country": "India",
        "product": "Fiber Internet 1 Gbps",
        "quantity": 390,
        "unitPrice": 12343,
        "totalAmount": 4813770,
        "status": "In progress",
        "createdBy": "Mr. Michael Harris",
        "orderDate": "2026-03-01",
        "id": "56e995ca-244f-49b2-b757-c4213b0a1565"
    },
    {
        "firstName": "Vinoth ",
        "lastName": "S",
        "email": "vinoth@gmail.com",
        "phone": "08925708902",
        "streetAddress": "xxxxxx",
        "city": "Theni",
        "state": "Tamil Nadu",
        "postalCode": "625513",
        "country": "India",
        "product": "5G Unlimited Mobile Plan",
        "quantity": 6,
        "unitPrice": 149,
        "totalAmount": 894,
        "status": "Pending",
        "createdBy": "Mr. Michael Harris",
        "orderDate": "2026-03-18",
        "id": "b9b917eb-6f8d-4824-a3c2-4bf3b18b088e"
    },
    {
        "firstName": "SUMANBABU",
        "lastName": "S",
        "email": "suman@gmail.com",
        "phone": "08925708902",
        "streetAddress": "xxxhe ",
        "city": "Theni",
        "state": "Tamil Nadu",
        "postalCode": "625513",
        "country": "India",
        "product": "5G Unlimited Mobile Plan",
        "quantity": 2,
        "unitPrice": 149,
        "totalAmount": 298,
        "status": "Completed",
        "createdBy": "Mr. Ryan Cooper",
        "orderDate": "2026-03-18",
        "id": "0e8dbec0-6b17-4c48-82e6-26e27849a1e1"
    }
]